planfact_api/__init__.py
planfact_api/models.py
planfact_api/pf_interaction.py
planfact_api/planfact_api.py
python_planfact-0.0.10.1.dist-info/LICENSE
python_planfact-0.0.10.1.dist-info/METADATA
python_planfact-0.0.10.1.dist-info/WHEEL
python_planfact-0.0.10.1.dist-info/top_level.txt
python_planfact-0.0.10.1.dist-info/RECORD
